README.md
setup.py
ngungu/__init__.py
ngungu.egg-info/PKG-INFO
ngungu.egg-info/SOURCES.txt
ngungu.egg-info/dependency_links.txt
ngungu.egg-info/requires.txt
ngungu.egg-info/top_level.txt
ngungu/dict/changzhou.json
ngungu/dict/changzhou.ocd2
ngungu/dict/cixi.json
ngungu/dict/cixi.ocd2
ngungu/dict/fuyang.json
ngungu/dict/fuyang.ocd2
ngungu/dict/guangdong.json
ngungu/dict/guangdong.ocd2
ngungu/dict/hangzhou.json
ngungu/dict/hangzhou.ocd2
ngungu/dict/jiading.json
ngungu/dict/jiading.ocd2
ngungu/dict/jiashan.json
ngungu/dict/jiashan.ocd2
ngungu/dict/jingjiang.json
ngungu/dict/jingjiang.ocd2
ngungu/dict/linping.json
ngungu/dict/linping.ocd2
ngungu/dict/ningbo.json
ngungu/dict/ningbo.ocd2
ngungu/dict/pinghu.json
ngungu/dict/pinghu.ocd2
ngungu/dict/ruao.json
ngungu/dict/ruao.ocd2
ngungu/dict/sanmen.json
ngungu/dict/sanmen.ocd2
ngungu/dict/shanghai.json
ngungu/dict/shanghai.ocd2
ngungu/dict/shaoxing.json
ngungu/dict/shaoxing.ocd2
ngungu/dict/sichuan.json
ngungu/dict/sichuan.ocd2
ngungu/dict/suichang.json
ngungu/dict/suichang.ocd2
ngungu/dict/suzhou.json
ngungu/dict/suzhou.ocd2
ngungu/dict/tiantai.json
ngungu/dict/tiantai.ocd2
ngungu/dict/tongxiang.json
ngungu/dict/tongxiang.ocd2
ngungu/dict/wenzhou.json
ngungu/dict/wenzhou.ocd2
ngungu/dict/wuxi.json
ngungu/dict/wuxi.ocd2
ngungu/dict/xiaoshan.json
ngungu/dict/xiaoshan.ocd2
ngungu/dict/xiashi.json
ngungu/dict/xiashi.ocd2
ngungu/dict/yixing.json
ngungu/dict/yixing.ocd2
ngungu/dict/youbu.json
ngungu/dict/youbu.ocd2
ngungu/dict/zhenru.json
ngungu/dict/zhenru.ocd2